<Canvas xmlns="http://schemas.microsoft.com/client/2007"
        xmlns:x="http://schemas.microsoft.com/winfx/2006/xaml"
        Loaded="javascript:root_Loaded">

	<TextBlock x:Name="CursorTextBlock" Width="16" Height="16" Canvas.Left="5" FontFamily="Verdana" FontSize="16" FontWeight="ExtraBold" Foreground="#FF006500" Text="_" />

	<TextBlock x:Name="Character1" Text="" Canvas.Left="10" Canvas.Top="10" FontFamily="Verdana" FontSize="16" Foreground="Green" />
	<TextBlock x:Name="Character2" Text="" Canvas.Left="28" Canvas.Top="10" FontFamily="Verdana" FontSize="16" Foreground="Green" />
	<TextBlock x:Name="Character3" Text="" Canvas.Left="46" Canvas.Top="10" FontFamily="Verdana" FontSize="16" Foreground="Green" />
	<TextBlock x:Name="Character4" Text="" Canvas.Left="64" Canvas.Top="10" FontFamily="Verdana" FontSize="16" Foreground="Green" />
	<TextBlock x:Name="Character5" Text="" Canvas.Left="82" Canvas.Top="10" FontFamily="Verdana" FontSize="16" Foreground="Green" />
	<TextBlock x:Name="Character6" Text="" Canvas.Left="100" Canvas.Top="10" FontFamily="Verdana" FontSize="16" Foreground="Green" />
	<TextBlock x:Name="Character7" Text="" Canvas.Left="118" Canvas.Top="10" FontFamily="Verdana" FontSize="16" Foreground="Green" />
	<TextBlock x:Name="Character8" Text="" Canvas.Left="136" Canvas.Top="10" FontFamily="Verdana" FontSize="16" Foreground="Green" />
	<TextBlock x:Name="Character9" Text="" Canvas.Left="154" Canvas.Top="10" FontFamily="Verdana" FontSize="16" Foreground="Green" />
	<TextBlock x:Name="Character10" Text="" Canvas.Left="172" Canvas.Top="10" FontFamily="Verdana" FontSize="16" Foreground="Green" />

	<TextBlock x:Name="Character11" Text="" Canvas.Left="190" Canvas.Top="10" FontFamily="Verdana" FontSize="16" Foreground="Green" />
	<TextBlock x:Name="Character12" Text="" Canvas.Left="208" Canvas.Top="10" FontFamily="Verdana" FontSize="16" Foreground="Green" />
	<TextBlock x:Name="Character13" Text="" Canvas.Left="226" Canvas.Top="10" FontFamily="Verdana" FontSize="16" Foreground="Green" />
	<TextBlock x:Name="Character14" Text="" Canvas.Left="244" Canvas.Top="10" FontFamily="Verdana" FontSize="16" Foreground="Green" />
	<TextBlock x:Name="Character15" Text="" Canvas.Left="262" Canvas.Top="10" FontFamily="Verdana" FontSize="16" Foreground="Green" />
	<TextBlock x:Name="Character16" Text="" Canvas.Left="280" Canvas.Top="10" FontFamily="Verdana" FontSize="16" Foreground="Green" />
	<TextBlock x:Name="Character17" Text="" Canvas.Left="298" Canvas.Top="10" FontFamily="Verdana" FontSize="16" Foreground="Green" />
	<TextBlock x:Name="Character18" Text="" Canvas.Left="316" Canvas.Top="10" FontFamily="Verdana" FontSize="16" Foreground="Green" />
	<TextBlock x:Name="Character19" Text="" Canvas.Left="334" Canvas.Top="10" FontFamily="Verdana" FontSize="16" Foreground="Green" />
	<TextBlock x:Name="Character20" Text="" Canvas.Left="352" Canvas.Top="10" FontFamily="Verdana" FontSize="16" Foreground="Green" />

	<TextBlock x:Name="Character21" Text="" Canvas.Left="10" Canvas.Top="28" FontFamily="Verdana" FontSize="16" Foreground="Green" />
	<TextBlock x:Name="Character22" Text="" Canvas.Left="28" Canvas.Top="28" FontFamily="Verdana" FontSize="16" Foreground="Green" />
	<TextBlock x:Name="Character23" Text="" Canvas.Left="46" Canvas.Top="28" FontFamily="Verdana" FontSize="16" Foreground="Green" />
	<TextBlock x:Name="Character24" Text="" Canvas.Left="64" Canvas.Top="28" FontFamily="Verdana" FontSize="16" Foreground="Green" />
	<TextBlock x:Name="Character25" Text="" Canvas.Left="82" Canvas.Top="28" FontFamily="Verdana" FontSize="16" Foreground="Green" />
	<TextBlock x:Name="Character26" Text="" Canvas.Left="100" Canvas.Top="28" FontFamily="Verdana" FontSize="16" Foreground="Green" />
	<TextBlock x:Name="Character27" Text="" Canvas.Left="118" Canvas.Top="28" FontFamily="Verdana" FontSize="16" Foreground="Green" />
	<TextBlock x:Name="Character28" Text="" Canvas.Left="136" Canvas.Top="28" FontFamily="Verdana" FontSize="16" Foreground="Green" />
	<TextBlock x:Name="Character29" Text="" Canvas.Left="154" Canvas.Top="28" FontFamily="Verdana" FontSize="16" Foreground="Green" />
	<TextBlock x:Name="Character30" Text="" Canvas.Left="172" Canvas.Top="28" FontFamily="Verdana" FontSize="16" Foreground="Green" />

	<TextBlock x:Name="Character31" Text="" Canvas.Left="190" Canvas.Top="28" FontFamily="Verdana" FontSize="16" Foreground="Green" />
	<TextBlock x:Name="Character32" Text="" Canvas.Left="208" Canvas.Top="28" FontFamily="Verdana" FontSize="16" Foreground="Green" />
	<TextBlock x:Name="Character33" Text="" Canvas.Left="226" Canvas.Top="28" FontFamily="Verdana" FontSize="16" Foreground="Green" />
	<TextBlock x:Name="Character34" Text="" Canvas.Left="244" Canvas.Top="28" FontFamily="Verdana" FontSize="16" Foreground="Green" />
	<TextBlock x:Name="Character35" Text="" Canvas.Left="262" Canvas.Top="28" FontFamily="Verdana" FontSize="16" Foreground="Green" />
	<TextBlock x:Name="Character36" Text="" Canvas.Left="280" Canvas.Top="28" FontFamily="Verdana" FontSize="16" Foreground="Green" />
	<TextBlock x:Name="Character37" Text="" Canvas.Left="298" Canvas.Top="28" FontFamily="Verdana" FontSize="16" Foreground="Green" />
	<TextBlock x:Name="Character38" Text="" Canvas.Left="316" Canvas.Top="28" FontFamily="Verdana" FontSize="16" Foreground="Green" />
	<TextBlock x:Name="Character39" Text="" Canvas.Left="334" Canvas.Top="28" FontFamily="Verdana" FontSize="16" Foreground="Green" />
	<TextBlock x:Name="Character40" Text="" Canvas.Left="352" Canvas.Top="28" FontFamily="Verdana" FontSize="16" Foreground="Green" />

	<TextBlock x:Name="Character41" Text="" Canvas.Left="10" Canvas.Top="46" FontFamily="Verdana" FontSize="16" Foreground="Green" />
	<TextBlock x:Name="Character42" Text="" Canvas.Left="28" Canvas.Top="46" FontFamily="Verdana" FontSize="16" Foreground="Green" />
	<TextBlock x:Name="Character43" Text="" Canvas.Left="46" Canvas.Top="46" FontFamily="Verdana" FontSize="16" Foreground="Green" />
	<TextBlock x:Name="Character44" Text="" Canvas.Left="64" Canvas.Top="46" FontFamily="Verdana" FontSize="16" Foreground="Green" />
	<TextBlock x:Name="Character45" Text="" Canvas.Left="82" Canvas.Top="46" FontFamily="Verdana" FontSize="16" Foreground="Green" />
	<TextBlock x:Name="Character46" Text="" Canvas.Left="100" Canvas.Top="46" FontFamily="Verdana" FontSize="16" Foreground="Green" />
	<TextBlock x:Name="Character47" Text="" Canvas.Left="118" Canvas.Top="46" FontFamily="Verdana" FontSize="16" Foreground="Green" />
	<TextBlock x:Name="Character48" Text="" Canvas.Left="136" Canvas.Top="46" FontFamily="Verdana" FontSize="16" Foreground="Green" />
	<TextBlock x:Name="Character49" Text="" Canvas.Left="154" Canvas.Top="46" FontFamily="Verdana" FontSize="16" Foreground="Green" />
	<TextBlock x:Name="Character50" Text="" Canvas.Left="172" Canvas.Top="46" FontFamily="Verdana" FontSize="16" Foreground="Green" />

	<TextBlock x:Name="Character51" Text="" Canvas.Left="190" Canvas.Top="46" FontFamily="Verdana" FontSize="16" Foreground="Green" />
	<TextBlock x:Name="Character52" Text="" Canvas.Left="208" Canvas.Top="46" FontFamily="Verdana" FontSize="16" Foreground="Green" />
	<TextBlock x:Name="Character53" Text="" Canvas.Left="226" Canvas.Top="46" FontFamily="Verdana" FontSize="16" Foreground="Green" />
	<TextBlock x:Name="Character54" Text="" Canvas.Left="244" Canvas.Top="46" FontFamily="Verdana" FontSize="16" Foreground="Green" />
	<TextBlock x:Name="Character55" Text="" Canvas.Left="262" Canvas.Top="46" FontFamily="Verdana" FontSize="16" Foreground="Green" />
	<TextBlock x:Name="Character56" Text="" Canvas.Left="280" Canvas.Top="46" FontFamily="Verdana" FontSize="16" Foreground="Green" />
	<TextBlock x:Name="Character57" Text="" Canvas.Left="298" Canvas.Top="46" FontFamily="Verdana" FontSize="16" Foreground="Green" />
	<TextBlock x:Name="Character58" Text="" Canvas.Left="316" Canvas.Top="46" FontFamily="Verdana" FontSize="16" Foreground="Green" />
	<TextBlock x:Name="Character59" Text="" Canvas.Left="334" Canvas.Top="46" FontFamily="Verdana" FontSize="16" Foreground="Green" />
	<TextBlock x:Name="Character60" Text="" Canvas.Left="352" Canvas.Top="46" FontFamily="Verdana" FontSize="16" Foreground="Green" />

	<TextBlock x:Name="Character61" Text="" Canvas.Left="10" Canvas.Top="64" FontFamily="Verdana" FontSize="16" Foreground="Green" />
	<TextBlock x:Name="Character62" Text="" Canvas.Left="28" Canvas.Top="64" FontFamily="Verdana" FontSize="16" Foreground="Green" />
	<TextBlock x:Name="Character63" Text="" Canvas.Left="46" Canvas.Top="64" FontFamily="Verdana" FontSize="16" Foreground="Green" />
	<TextBlock x:Name="Character64" Text="" Canvas.Left="64" Canvas.Top="64" FontFamily="Verdana" FontSize="16" Foreground="Green" />
	<TextBlock x:Name="Character65" Text="" Canvas.Left="82" Canvas.Top="64" FontFamily="Verdana" FontSize="16" Foreground="Green" />
	<TextBlock x:Name="Character66" Text="" Canvas.Left="100" Canvas.Top="64" FontFamily="Verdana" FontSize="16" Foreground="Green" />
	<TextBlock x:Name="Character67" Text="" Canvas.Left="118" Canvas.Top="64" FontFamily="Verdana" FontSize="16" Foreground="Green" />
	<TextBlock x:Name="Character68" Text="" Canvas.Left="136" Canvas.Top="64" FontFamily="Verdana" FontSize="16" Foreground="Green" />
	<TextBlock x:Name="Character69" Text="" Canvas.Left="154" Canvas.Top="64" FontFamily="Verdana" FontSize="16" Foreground="Green" />
	<TextBlock x:Name="Character70" Text="" Canvas.Left="172" Canvas.Top="64" FontFamily="Verdana" FontSize="16" Foreground="Green" />

	<TextBlock x:Name="Character71" Text="" Canvas.Left="190" Canvas.Top="64" FontFamily="Verdana" FontSize="16" Foreground="Green" />
	<TextBlock x:Name="Character72" Text="" Canvas.Left="208" Canvas.Top="64" FontFamily="Verdana" FontSize="16" Foreground="Green" />
	<TextBlock x:Name="Character73" Text="" Canvas.Left="226" Canvas.Top="64" FontFamily="Verdana" FontSize="16" Foreground="Green" />
	<TextBlock x:Name="Character74" Text="" Canvas.Left="244" Canvas.Top="64" FontFamily="Verdana" FontSize="16" Foreground="Green" />
	<TextBlock x:Name="Character75" Text="" Canvas.Left="262" Canvas.Top="64" FontFamily="Verdana" FontSize="16" Foreground="Green" />
	<TextBlock x:Name="Character76" Text="" Canvas.Left="280" Canvas.Top="64" FontFamily="Verdana" FontSize="16" Foreground="Green" />
	<TextBlock x:Name="Character77" Text="" Canvas.Left="298" Canvas.Top="64" FontFamily="Verdana" FontSize="16" Foreground="Green" />
	<TextBlock x:Name="Character78" Text="" Canvas.Left="316" Canvas.Top="64" FontFamily="Verdana" FontSize="16" Foreground="Green" />
	<TextBlock x:Name="Character79" Text="" Canvas.Left="334" Canvas.Top="64" FontFamily="Verdana" FontSize="16" Foreground="Green" />
	<TextBlock x:Name="Character80" Text="" Canvas.Left="352" Canvas.Top="64" FontFamily="Verdana" FontSize="16" Foreground="Green" />

	<TextBlock x:Name="Character81" Text="" Canvas.Left="10" Canvas.Top="82" FontFamily="Verdana" FontSize="16" Foreground="Green" />
	<TextBlock x:Name="Character82" Text="" Canvas.Left="28" Canvas.Top="82" FontFamily="Verdana" FontSize="16" Foreground="Green" />
	<TextBlock x:Name="Character83" Text="" Canvas.Left="46" Canvas.Top="82" FontFamily="Verdana" FontSize="16" Foreground="Green" />
	<TextBlock x:Name="Character84" Text="" Canvas.Left="64" Canvas.Top="82" FontFamily="Verdana" FontSize="16" Foreground="Green" />
	<TextBlock x:Name="Character85" Text="" Canvas.Left="82" Canvas.Top="82" FontFamily="Verdana" FontSize="16" Foreground="Green" />
	<TextBlock x:Name="Character86" Text="" Canvas.Left="100" Canvas.Top="82" FontFamily="Verdana" FontSize="16" Foreground="Green" />
	<TextBlock x:Name="Character87" Text="" Canvas.Left="118" Canvas.Top="82" FontFamily="Verdana" FontSize="16" Foreground="Green" />
	<TextBlock x:Name="Character88" Text="" Canvas.Left="136" Canvas.Top="82" FontFamily="Verdana" FontSize="16" Foreground="Green" />
	<TextBlock x:Name="Character89" Text="" Canvas.Left="154" Canvas.Top="82" FontFamily="Verdana" FontSize="16" Foreground="Green" />
	<TextBlock x:Name="Character90" Text="" Canvas.Left="172" Canvas.Top="82" FontFamily="Verdana" FontSize="16" Foreground="Green" />

	<TextBlock x:Name="Character91" Text="" Canvas.Left="190" Canvas.Top="82" FontFamily="Verdana" FontSize="16" Foreground="Green" />
	<TextBlock x:Name="Character92" Text="" Canvas.Left="208" Canvas.Top="82" FontFamily="Verdana" FontSize="16" Foreground="Green" />
	<TextBlock x:Name="Character93" Text="" Canvas.Left="226" Canvas.Top="82" FontFamily="Verdana" FontSize="16" Foreground="Green" />
	<TextBlock x:Name="Character94" Text="" Canvas.Left="244" Canvas.Top="82" FontFamily="Verdana" FontSize="16" Foreground="Green" />
	<TextBlock x:Name="Character95" Text="" Canvas.Left="262" Canvas.Top="82" FontFamily="Verdana" FontSize="16" Foreground="Green" />
	<TextBlock x:Name="Character96" Text="" Canvas.Left="280" Canvas.Top="82" FontFamily="Verdana" FontSize="16" Foreground="Green" />
	<TextBlock x:Name="Character97" Text="" Canvas.Left="298" Canvas.Top="82" FontFamily="Verdana" FontSize="16" Foreground="Green" />
	<TextBlock x:Name="Character98" Text="" Canvas.Left="316" Canvas.Top="82" FontFamily="Verdana" FontSize="16" Foreground="Green" />
	<TextBlock x:Name="Character99" Text="" Canvas.Left="334" Canvas.Top="82" FontFamily="Verdana" FontSize="16" Foreground="Green" />
	<TextBlock x:Name="Character100" Text="" Canvas.Left="352" Canvas.Top="82" FontFamily="Verdana" FontSize="16" Foreground="Green" />

	<TextBlock x:Name="Character101" Text="" Canvas.Left="10" Canvas.Top="100" FontFamily="Verdana" FontSize="16" Foreground="Green" />
	<TextBlock x:Name="Character102" Text="" Canvas.Left="28" Canvas.Top="100" FontFamily="Verdana" FontSize="16" Foreground="Green" />
	<TextBlock x:Name="Character103" Text="" Canvas.Left="46" Canvas.Top="100" FontFamily="Verdana" FontSize="16" Foreground="Green" />
	<TextBlock x:Name="Character104" Text="" Canvas.Left="64" Canvas.Top="100" FontFamily="Verdana" FontSize="16" Foreground="Green" />
	<TextBlock x:Name="Character105" Text="" Canvas.Left="82" Canvas.Top="100" FontFamily="Verdana" FontSize="16" Foreground="Green" />
	<TextBlock x:Name="Character106" Text="" Canvas.Left="100" Canvas.Top="100" FontFamily="Verdana" FontSize="16" Foreground="Green" />
	<TextBlock x:Name="Character107" Text="" Canvas.Left="118" Canvas.Top="100" FontFamily="Verdana" FontSize="16" Foreground="Green" />
	<TextBlock x:Name="Character108" Text="" Canvas.Left="136" Canvas.Top="100" FontFamily="Verdana" FontSize="16" Foreground="Green" />
	<TextBlock x:Name="Character109" Text="" Canvas.Left="154" Canvas.Top="100" FontFamily="Verdana" FontSize="16" Foreground="Green" />
	<TextBlock x:Name="Character110" Text="" Canvas.Left="172" Canvas.Top="100" FontFamily="Verdana" FontSize="16" Foreground="Green" />

	<TextBlock x:Name="Character111" Text="" Canvas.Left="190" Canvas.Top="100" FontFamily="Verdana" FontSize="16" Foreground="Green" />
	<TextBlock x:Name="Character112" Text="" Canvas.Left="208" Canvas.Top="100" FontFamily="Verdana" FontSize="16" Foreground="Green" />
	<TextBlock x:Name="Character113" Text="" Canvas.Left="226" Canvas.Top="100" FontFamily="Verdana" FontSize="16" Foreground="Green" />
	<TextBlock x:Name="Character114" Text="" Canvas.Left="244" Canvas.Top="100" FontFamily="Verdana" FontSize="16" Foreground="Green" />
	<TextBlock x:Name="Character115" Text="" Canvas.Left="262" Canvas.Top="100" FontFamily="Verdana" FontSize="16" Foreground="Green" />
	<TextBlock x:Name="Character116" Text="" Canvas.Left="280" Canvas.Top="100" FontFamily="Verdana" FontSize="16" Foreground="Green" />
	<TextBlock x:Name="Character117" Text="" Canvas.Left="298" Canvas.Top="100" FontFamily="Verdana" FontSize="16" Foreground="Green" />
	<TextBlock x:Name="Character118" Text="" Canvas.Left="316" Canvas.Top="100" FontFamily="Verdana" FontSize="16" Foreground="Green" />
	<TextBlock x:Name="Character119" Text="" Canvas.Left="334" Canvas.Top="100" FontFamily="Verdana" FontSize="16" Foreground="Green" />
	<TextBlock x:Name="Character120" Text="" Canvas.Left="352" Canvas.Top="100" FontFamily="Verdana" FontSize="16" Foreground="Green" />

	<TextBlock x:Name="Character121" Text="" Canvas.Left="10" Canvas.Top="118" FontFamily="Verdana" FontSize="16" Foreground="Green" />
	<TextBlock x:Name="Character122" Text="" Canvas.Left="28" Canvas.Top="118" FontFamily="Verdana" FontSize="16" Foreground="Green" />
	<TextBlock x:Name="Character123" Text="" Canvas.Left="46" Canvas.Top="118" FontFamily="Verdana" FontSize="16" Foreground="Green" />
	<TextBlock x:Name="Character124" Text="" Canvas.Left="64" Canvas.Top="118" FontFamily="Verdana" FontSize="16" Foreground="Green" />
	<TextBlock x:Name="Character125" Text="" Canvas.Left="82" Canvas.Top="118" FontFamily="Verdana" FontSize="16" Foreground="Green" />
	<TextBlock x:Name="Character126" Text="" Canvas.Left="100" Canvas.Top="118" FontFamily="Verdana" FontSize="16" Foreground="Green" />
	<TextBlock x:Name="Character127" Text="" Canvas.Left="118" Canvas.Top="118" FontFamily="Verdana" FontSize="16" Foreground="Green" />
	<TextBlock x:Name="Character128" Text="" Canvas.Left="136" Canvas.Top="118" FontFamily="Verdana" FontSize="16" Foreground="Green" />
	<TextBlock x:Name="Character129" Text="" Canvas.Left="154" Canvas.Top="118" FontFamily="Verdana" FontSize="16" Foreground="Green" />
	<TextBlock x:Name="Character130" Text="" Canvas.Left="172" Canvas.Top="118" FontFamily="Verdana" FontSize="16" Foreground="Green" />

	<TextBlock x:Name="Character131" Text="" Canvas.Left="190" Canvas.Top="118" FontFamily="Verdana" FontSize="16" Foreground="Green" />
	<TextBlock x:Name="Character132" Text="" Canvas.Left="208" Canvas.Top="118" FontFamily="Verdana" FontSize="16" Foreground="Green" />
	<TextBlock x:Name="Character133" Text="" Canvas.Left="226" Canvas.Top="118" FontFamily="Verdana" FontSize="16" Foreground="Green" />
	<TextBlock x:Name="Character134" Text="" Canvas.Left="244" Canvas.Top="118" FontFamily="Verdana" FontSize="16" Foreground="Green" />
	<TextBlock x:Name="Character135" Text="" Canvas.Left="262" Canvas.Top="118" FontFamily="Verdana" FontSize="16" Foreground="Green" />
	<TextBlock x:Name="Character136" Text="" Canvas.Left="280" Canvas.Top="118" FontFamily="Verdana" FontSize="16" Foreground="Green" />
	<TextBlock x:Name="Character137" Text="" Canvas.Left="298" Canvas.Top="118" FontFamily="Verdana" FontSize="16" Foreground="Green" />
	<TextBlock x:Name="Character138" Text="" Canvas.Left="316" Canvas.Top="118" FontFamily="Verdana" FontSize="16" Foreground="Green" />
	<TextBlock x:Name="Character139" Text="" Canvas.Left="334" Canvas.Top="118" FontFamily="Verdana" FontSize="16" Foreground="Green" />
	<TextBlock x:Name="Character140" Text="" Canvas.Left="352" Canvas.Top="118" FontFamily="Verdana" FontSize="16" Foreground="Green" />
</Canvas>